p3exporter/__init__.py
p3exporter/__main__.py
p3exporter/web.py
p3exporter/cache/__init__.py
p3exporter/collector/__init__.py
p3exporter/collector/example.py
p3exporter/collector/loadavg.py
p3exporter/collector/netdev.py
p3exporter/static/style.css
p3exporter/templates/index.html
p3exporter-1.2.0.dist-info/LICENSE
p3exporter-1.2.0.dist-info/METADATA
p3exporter-1.2.0.dist-info/WHEEL
p3exporter-1.2.0.dist-info/entry_points.txt
p3exporter-1.2.0.dist-info/top_level.txt
p3exporter-1.2.0.dist-info/RECORD
