Metadata-Version: 2.1
Name: p3exporter
Version: 1.2.0
Summary: Python Programmable Prometheus exporter
Home-page: https://codeaffen.org/projects/p3exporter
Author: Christian Meißner
Author-email: cme@codeaffen.org
License: GPLv3
Keywords: monitoring prometheus exporter example
Platform: UNKNOWN
Classifier: License :: OSI Approved :: GNU General Public License v3 (GPLv3)
Classifier: Intended Audience :: Developers
Classifier: Intended Audience :: System Administrators
Classifier: Topic :: System :: Monitoring
Classifier: Programming Language :: Python :: 3.7
Classifier: Programming Language :: Python :: 3.8
Classifier: Programming Language :: Python :: 3.9
Classifier: Programming Language :: Python :: 3.10
License-File: LICENSE
Requires-Dist: flask
Requires-Dist: inflection
Requires-Dist: netifaces
Requires-Dist: prometheus-client
Requires-Dist: PyYAML
